railway/__init__.py
railway/py.typed
railway/cli/__init__.py
railway/cli/backup.py
railway/cli/compatibility.py
railway/cli/docs.py
railway/cli/init.py
railway/cli/list.py
railway/cli/main.py
railway/cli/new.py
railway/cli/preview_display.py
railway/cli/run.py
railway/cli/show.py
railway/cli/sync.py
railway/cli/update.py
railway/core/__init__.py
railway/core/config.py
railway/core/contract.py
railway/core/decorators.py
railway/core/errors.py
railway/core/exit_contract.py
railway/core/logging.py
railway/core/pipeline.py
railway/core/project_discovery.py
railway/core/project_metadata.py
railway/core/registry.py
railway/core/resolver.py
railway/core/retry.py
railway/core/settings.py
railway/core/type_check.py
railway/core/version_checker.py
railway/core/dag/__init__.py
railway/core/dag/callbacks.py
railway/core/dag/codegen.py
railway/core/dag/dependency_extraction.py
railway/core/dag/dependency_validator.py
railway/core/dag/errors.py
railway/core/dag/field_dependency.py
railway/core/dag/outcome.py
railway/core/dag/parser.py
railway/core/dag/runner.py
railway/core/dag/schema.py
railway/core/dag/state.py
railway/core/dag/type_checker.py
railway/core/dag/types.py
railway/core/dag/validator.py
railway/migrations/__init__.py
railway/migrations/backup.py
railway/migrations/changes.py
railway/migrations/config_merger.py
railway/migrations/diff.py
railway/migrations/executor.py
railway/migrations/field_dependency.py
railway/migrations/preview.py
railway/migrations/preview_types.py
railway/migrations/registry.py
railway/migrations/types.py
railway/migrations/yaml_converter.py
railway/migrations/definitions/__init__.py
railway/migrations/definitions/v0_10_to_v0_11.py
railway/migrations/definitions/v0_11_to_v0_12.py
railway/migrations/definitions/v0_12_1_to_v0_12_2.py
railway/migrations/definitions/v0_13_3_to_v0_13_4.py
railway/utils/__init__.py
railway/readme.md
railway_framework-0.13.5.dist-info/METADATA
railway_framework-0.13.5.dist-info/WHEEL
railway_framework-0.13.5.dist-info/entry_points.txt
railway_framework-0.13.5.dist-info/licenses/LICENSE
railway_framework-0.13.5.dist-info/RECORD
